nmgr/actions.py
nmgr/cli.py
nmgr/config.py
nmgr/data/completion.bash
nmgr/data/config.toml
nmgr/jobs.py
nmgr/log.py
nmgr/nomad.py
nmgr/registry.py
nmgr/targets.py
nmgr-0.3.1.dist-info/LICENSE
nmgr-0.3.1.dist-info/METADATA
nmgr-0.3.1.dist-info/WHEEL
nmgr-0.3.1.dist-info/entry_points.txt
nmgr-0.3.1.dist-info/RECORD
