Metadata-Version: 2.1
Name: nmgr
Version: 0.3.1
Summary: Nomad job management tool
Home-page: https://github.com/cycneuramus/nmgr
License: GPL-3.0-only
Keywords: nomad
Author: cycneuramus
Author-email: 56681631+cycneuramus@users.noreply.github.com
Requires-Python: >=3.11
Classifier: License :: OSI Approved :: GNU General Public License v3 (GPLv3)
Classifier: Programming Language :: Python :: 3
Classifier: Programming Language :: Python :: 3.11
Classifier: Programming Language :: Python :: 3.12
Classifier: Programming Language :: Python :: 3.13
Project-URL: Repository, https://github.com/cycneuramus/nmgr
